pyarchetype/__init__.py
pyarchetype/pyarchetype.py
pyarchetype/templates/__init__.py
pyarchetype/templates/templates.py
pyarchetype-0.1.12.dist-info/LICENSE
pyarchetype-0.1.12.dist-info/METADATA
pyarchetype-0.1.12.dist-info/WHEEL
pyarchetype-0.1.12.dist-info/entry_points.txt
pyarchetype-0.1.12.dist-info/top_level.txt
pyarchetype-0.1.12.dist-info/RECORD
