Metadata-Version: 2.1
Name: pyarchetype
Version: 0.1.12
Summary: Your tool to create the skeleton of python projects
Author-email: Jordi Redondo <jordipromotions@gmail.com>
Project-URL: Homepage, https://github.com/redcorjo/pyarchetype
Project-URL: Bug Tracker, https://github.com/redcorjo/pyarchetype/issues
Classifier: Programming Language :: Python :: 3
Classifier: License :: OSI Approved :: MIT License
Classifier: Operating System :: OS Independent
Requires-Python: >=3.7
License-File: LICENSE
Requires-Dist: Jinja2 (>=3.1.2)
Requires-Dist: importlib-metadata (==6.0.0)
